iccas/__init__.py
iccas/__main__.py
iccas/_caching.py
iccas/checks.py
iccas/loading.py
iccas/processing.py
iccas/queries.py
iccas/types.py
iccas/charts/__init__.py
iccas/charts/area.py
iccas/charts/bar.py
iccas/charts/common.py
iccas/cli/__init__.py
iccas/cli/main.py
iccas/i18n/__init__.py
iccas/i18n/lib.py
iccas/i18n/translations.yml
iccas-0.2.0.dist-info/LICENSE
iccas-0.2.0.dist-info/METADATA
iccas-0.2.0.dist-info/WHEEL
iccas-0.2.0.dist-info/entry_points.txt
iccas-0.2.0.dist-info/top_level.txt
iccas-0.2.0.dist-info/RECORD
