Metadata-Version: 2.1
Name: iccas
Version: 0.2.0
Summary: Helper library for the ICCAS dataset
Home-page: https://github.com/janLuke/iccas-python
Author: Gianluca Gippetto
Author-email: gianluca.gippetto@gmail.com
License: MIT license
Keywords: iccas
Platform: UNKNOWN
Classifier: Intended Audience :: Developers
Classifier: License :: OSI Approved :: MIT License
Classifier: Natural Language :: English
Classifier: Programming Language :: Python :: 3
Classifier: Programming Language :: Python :: 3.7
Classifier: Programming Language :: Python :: 3.8
Requires-Python: >=3.7
Requires-Dist: pandas
Requires-Dist: requests
Requires-Dist: numpy
Requires-Dist: url-normalize
Requires-Dist: pyyaml
Requires-Dist: matplotlib
Requires-Dist: seaborn
Provides-Extra: cli
Requires-Dist: cloup ; extra == 'cli'
Requires-Dist: click ; extra == 'cli'
Requires-Dist: tqdm ; extra == 'cli'
Requires-Dist: pathvalidate ; extra == 'cli'
